[
  {
    "name": "自學四年通過日檢 N2 心得",
    "views": 7900,
    "link": "https://medium.com/%E6%97%A5%E8%AA%9E%E5%85%AB%E7%99%BE%E5%B1%8B/%E8%87%AA%E5%AD%B8%E5%9B%9B%E5%B9%B4%E9%80%9A%E9%81%8E%E6%97%A5%E6%AA%A2-n2-%E5%BF%83%E5%BE%97-2e91435250c9",
    "claps": 97
  },
  {
    "name": "前端面試總結",
    "views": 4600,
    "link": "https://medium.com/d-d-mag/%E5%89%8D%E7%AB%AF%E9%9D%A2%E8%A9%A6%E7%B8%BD%E7%B5%90-dfe8bf07bfe1",
    "claps": 304
  },
  {
    "name": "淺談降維方法中的 PCA 與 t-SNE",
    "views": 1500,
    "claps": 76,
    "link": "https://medium.com/d-d-mag/%E6%B7%BA%E8%AB%87%E5%85%A9%E7%A8%AE%E9%99%8D%E7%B6%AD%E6%96%B9%E6%B3%95-pca-%E8%88%87-t-sne-d4254916925b"
  },
  {
    "name": "日語學習資源總整理",
    "views": 908,
    "claps": 9,
    "link": "https://medium.com/%E6%97%A5%E8%AA%9E%E5%85%AB%E7%99%BE%E5%B1%8B/%E6%97%A5%E6%96%87%E5%AD%B8%E7%BF%92%E8%B3%87%E6%BA%90%E7%B8%BD%E6%95%B4%E7%90%86-fd3d065df01a"
  },
  {
    "name": "日本服務業用語",
    "views": 755,
    "claps": 8,
    "link": "https://medium.com/%E6%97%A5%E8%AA%9E%E5%85%AB%E7%99%BE%E5%B1%8B/%E6%97%A5%E6%9C%AC%E6%9C%8D%E5%8B%99%E6%A5%AD%E7%94%A8%E8%AA%9E-ad382a7e034b"
  },
  {
    "name": "狂歡雙 11 — 祝我生日快樂",
    "views": 550,
    "claps": 74,
    "link": "https://medium.com/@Shurado/%E7%8B%82%E6%AD%A1%E9%9B%99-11-%E7%A5%9D%E6%88%91%E7%94%9F%E6%97%A5%E5%BF%AB%E6%A8%82-bfabdca3df24"
  },
  {
    "name": "為什麼台灣人無法抵制全聯",
    "views": 292,
    "claps": 33,
    "link": "https://medium.com/@Shurado/為什麼台灣人無法抵制全聯-f54c358c868a"
  },
  {
    "name": "淺析幾個 ramda 當中的 API",
    "link": "https://medium.com/d-d-mag/%E6%B7%BA%E6%9E%90%E5%B9%BE%E5%80%8B-ramda-%E7%95%B6%E4%B8%AD%E7%9A%84-api-c399a3f73c68",
    "views": 103,
    "claps": 15
  },
  {
    "name": "你可能不知道的 Sass 技巧",
    "views": 153,
    "claps": 15,
    "link": "https://medium.com/d-d-mag/%E4%BD%A0%E5%8F%AF%E8%83%BD%E4%B8%8D%E7%9F%A5%E9%81%93%E7%9A%84-sass-%E6%8A%80%E5%B7%A7-c97d4d5e0fc4"
  },
  {
    "name": "深入探討 redux 與 react-redux",
    "views": 100,
    "claps": 1,
    "link": "https://medium.com/d-d-mag/%E6%B7%B1%E5%85%A5%E6%8E%A2%E8%A8%8E-redux-%E8%88%87-react-redux-f6230d6ae83f"
  },
  {
    "name": "PostgreSQL 筆記 - 索引",
    "views": 99,
    "claps": 2,
    "link": "https://medium.com/d-d-mag/postgresql-%E7%95%B6%E4%B8%AD%E7%9A%84-index-e7e1e8d9340c"
  }
]
